ansys_sphinx_theme/__init__.py
ansys_sphinx_theme/assets/scripts/.gitkeep
ansys_sphinx_theme/assets/styles/.gitkeep
ansys_sphinx_theme/assets/styles/ansys-sphinx-theme-variable.scss
ansys_sphinx_theme/assets/styles/ansys-sphinx-theme.scss
ansys_sphinx_theme/assets/styles/ast-search.scss
ansys_sphinx_theme/assets/styles/breadcrumbs.scss
ansys_sphinx_theme/assets/styles/nbsphinx.scss
ansys_sphinx_theme/assets/styles/pydata-sphinx-theme-custom.scss
ansys_sphinx_theme/assets/styles/sphinx-design.scss
ansys_sphinx_theme/assets/styles/sphinx-gallery.scss
ansys_sphinx_theme/assets/styles/table-custom.scss
ansys_sphinx_theme/assets/styles/whatsnew.scss
ansys_sphinx_theme/cheatsheet.py
ansys_sphinx_theme/examples/__init__.py
ansys_sphinx_theme/examples/sample_func.py
ansys_sphinx_theme/examples/samples.py
ansys_sphinx_theme/examples/type_hint_example.py
ansys_sphinx_theme/extension/__init__.py
ansys_sphinx_theme/extension/autoapi.py
ansys_sphinx_theme/extension/linkcode.py
ansys_sphinx_theme/latex/404.html
ansys_sphinx_theme/latex/__init__.py
ansys_sphinx_theme/latex/cover.tex
ansys_sphinx_theme/navbar_dropdown.py
ansys_sphinx_theme/search/__init__.py
ansys_sphinx_theme/search/fuse_search.py
ansys_sphinx_theme/theme/ansys_sphinx_theme/_templates/autoapi/index.rst
ansys_sphinx_theme/theme/ansys_sphinx_theme/_templates/autoapi/python/class.rst
ansys_sphinx_theme/theme/ansys_sphinx_theme/_templates/autoapi/python/module.rst
ansys_sphinx_theme/theme/ansys_sphinx_theme/_templates/autosummary/base.rst
ansys_sphinx_theme/theme/ansys_sphinx_theme/_templates/autosummary/class.rst
ansys_sphinx_theme/theme/ansys_sphinx_theme/_templates/sourcelink.html
ansys_sphinx_theme/theme/ansys_sphinx_theme/components/announcement_version.html
ansys_sphinx_theme/theme/ansys_sphinx_theme/components/ast-search-button.html
ansys_sphinx_theme/theme/ansys_sphinx_theme/components/breadcrumbs.html
ansys_sphinx_theme/theme/ansys_sphinx_theme/components/cheatsheet_sidebar.html
ansys_sphinx_theme-1.6.4.dist-info/LICENSE
ansys_sphinx_theme-1.6.4.dist-info/METADATA
ansys_sphinx_theme-1.6.4.dist-info/WHEEL
ansys_sphinx_theme-1.6.4.dist-info/entry_points.txt
ansys_sphinx_theme-1.6.4.dist-info/RECORD