Metadata-Version: 2.1
Name: ansys-sphinx-theme
Version: 1.6.4
Summary: A theme devised by ANSYS, Inc. for Sphinx documentation.
Author-Email: "ANSYS, Inc." <pyansys.core@ansys.com>
Maintainer-Email: "ANSYS, Inc." <pyansys.core@ansys.com>
License: MIT License
Classifier: Development Status :: 4 - Beta
Classifier: Framework :: Sphinx
Classifier: Framework :: Sphinx :: Theme
Classifier: License :: OSI Approved :: MIT License
Classifier: Operating System :: OS Independent
Classifier: Programming Language :: Python :: 3.10
Classifier: Programming Language :: Python :: 3.11
Classifier: Programming Language :: Python :: 3.12
Classifier: Programming Language :: Python :: 3.13
Project-URL: Home, https://sphinxdocs.ansys.com/
Project-URL: Source, https://github.com/ansys/ansys-sphinx-theme
Project-URL: Tracker, https://github.com/ansys/ansys-sphinx-theme/issues
Project-URL: Documentation, https://sphinxdocs.ansys.com/
Requires-Python: <4,>=3.10
Requires-Dist: importlib-metadata>=4.0
Requires-Dist: Jinja2>=3.1.2
Requires-Dist: pdf2image>=1.17.0
Requires-Dist: pydata-sphinx-theme<0.17,>=0.15.4
Requires-Dist: PyYAML>=6.0
Requires-Dist: Sphinx>=6.1.0
Provides-Extra: autoapi
Requires-Dist: sphinx-autoapi==3.6.1; extra == "autoapi"
Requires-Dist: sphinx-design==0.6.1; extra == "autoapi"
Requires-Dist: sphinx-jinja==2.0.2; extra == "autoapi"
Provides-Extra: doc
Requires-Dist: jupytext==1.17.3; extra == "doc"
Requires-Dist: nbsphinx==0.9.7; extra == "doc"
Requires-Dist: notebook==7.4.5; extra == "doc"
Requires-Dist: numpydoc==1.9.0; extra == "doc"
Requires-Dist: pandas==2.3.2; extra == "doc"
Requires-Dist: Pillow>=9.0; extra == "doc"
Requires-Dist: plotly==6.3.0; extra == "doc"
Requires-Dist: PyGitHub==2.7.0; extra == "doc"
Requires-Dist: pyvista[jupyter]==0.46.2; extra == "doc"
Requires-Dist: PyYAML==6.0.2; extra == "doc"
Requires-Dist: requests==2.32.5; extra == "doc"
Requires-Dist: sphinx-autoapi==3.6.1; extra == "doc"
Requires-Dist: sphinx-copybutton==0.5.2; extra == "doc"
Requires-Dist: sphinx-design==0.6.1; extra == "doc"
Requires-Dist: sphinx-gallery==0.19.0; extra == "doc"
Requires-Dist: sphinx-jinja==2.0.2; extra == "doc"
Requires-Dist: sphinx-notfound-page==1.1.0; extra == "doc"
Requires-Dist: sphinx-theme-builder[cli]==0.2.0b2; extra == "doc"
Requires-Dist: tox==4.28.4; extra == "doc"
Provides-Extra: changelog
Requires-Dist: PyYAML==6.0.2; extra == "changelog"
Requires-Dist: sphinx-design==0.6.1; extra == "changelog"
